{
  "_type" : {
    "_name" : "ActionsInvocationRecord"
  },
  "actions" : {
    "_type" : {
      "_name" : "Array"
    },
    "_values" : [
      {
        "_type" : {
          "_name" : "ActionRecord"
        },
        "actionResult" : {
          "_type" : {
            "_name" : "ActionResult"
          },
          "coverage" : {
            "_type" : {
              "_name" : "CodeCoverageInfo"
            },
            "archiveRef" : {
              "_type" : {
                "_name" : "Reference"
              },
              "id" : {
                "_type" : {
                  "_name" : "String"
                },
                "_value" : "0~Ti9mgv53iDZIRy8Ys-MRq2eRuV8XTjdqaKKT3HhuYQqR90HoK1nktVtVuqT0k8Pt0W-jZeH0CCYUKXlG4KIhxg=="
              }
            },
            "hasCoverageData" : {
              "_type" : {
                "_name" : "Bool"
              },
              "_value" : "true"
            },
            "reportRef" : {
              "_type" : {
                "_name" : "Reference"
              },
              "id" : {
                "_type" : {
                  "_name" : "String"
                },
                "_value" : "0~jR9YI2eYTb3OAvUaSBdDQr_L6lnUNV_2IjXLY-qRj2l3cSqez4adMzHqZRP3NkoAsvwIjMIKf7r29Pcq4052Vw=="
              }
            }
          },
          "diagnosticsRef" : {
            "_type" : {
              "_name" : "Reference"
            },
            "id" : {
              "_type" : {
                "_name" : "String"
              },
              "_value" : "0~5Vx7AXkTZ3GZvpBFZQnLC1vHyWAY-5orQ6YO3zIFEtX432h-yEvb4WDY4KTsm2fc9w8rcNXHm9P---jm__4a6g=="
            }
          },
          "issues" : {
            "_type" : {
              "_name" : "ResultIssueSummaries"
            }
          },
          "logRef" : {
            "_type" : {
              "_name" : "Reference"
            },
            "id" : {
              "_type" : {
                "_name" : "String"
              },
              "_value" : "0~hDllaaKpaZOty_DJ6JFw0XPLRRgSk8ZQRWH4HcrKi3tN2FSynkt6YDsRTh6QkCJ3vCtox3TEWk5UQC9IschliQ=="
            },
            "targetType" : {
              "_type" : {
                "_name" : "TypeDefinition"
              },
              "name" : {
                "_type" : {
                  "_name" : "String"
                },
                "_value" : "ActivityLogSection"
              }
            }
          },
          "metrics" : {
            "_type" : {
              "_name" : "ResultMetrics"
            }
          },
          "resultName" : {
            "_type" : {
              "_name" : "String"
            },
            "_value" : "action"
          },
          "status" : {
            "_type" : {
              "_name" : "String"
            },
            "_value" : "succeeded"
          },
          "testsRef" : {
            "_type" : {
              "_name" : "Reference"
            },
            "id" : {
              "_type" : {
                "_name" : "String"
              },
              "_value" : "0~F4YMiC7gtNZZK5wgsNtlz_S5OXBsN_7A-aNWw0CsHiOTMnORgmTCbEcZLSg7ChrJo_KHLf9Ma4mlxL9MvxLkeQ=="
            },
            "targetType" : {
              "_type" : {
                "_name" : "TypeDefinition"
              },
              "name" : {
                "_type" : {
                  "_name" : "String"
                },
                "_value" : "ActionTestPlanRunSummaries"
              }
            }
          }
        },
        "buildResult" : {
          "_type" : {
            "_name" : "ActionResult"
          },
          "coverage" : {
            "_type" : {
              "_name" : "CodeCoverageInfo"
            }
          },
          "issues" : {
            "_type" : {
              "_name" : "ResultIssueSummaries"
            }
          },
          "logRef" : {
            "_type" : {
              "_name" : "Reference"
            },
            "id" : {
              "_type" : {
                "_name" : "String"
              },
              "_value" : "0~u8_94DW2tbJu0_yT4TsJ10JL99-i9jIfvHfMsz50mcUQF3NbWVzTRhZqt6AYZ4NP-TidtxsKdRwm9LqBpkQD5A=="
            },
            "targetType" : {
              "_type" : {
                "_name" : "TypeDefinition"
              },
              "name" : {
                "_type" : {
                  "_name" : "String"
                },
                "_value" : "ActivityLogSection"
              }
            }
          },
          "metrics" : {
            "_type" : {
              "_name" : "ResultMetrics"
            }
          },
          "resultName" : {
            "_type" : {
              "_name" : "String"
            },
            "_value" : "build"
          },
          "status" : {
            "_type" : {
              "_name" : "String"
            },
            "_value" : "succeeded"
          }
        },
        "endedTime" : {
          "_type" : {
            "_name" : "Date"
          },
          "_value" : "2024-11-02T22:12:31.600+0900"
        },
        "runDestination" : {
          "_type" : {
            "_name" : "ActionRunDestinationRecord"
          },
          "displayName" : {
            "_type" : {
              "_name" : "String"
            },
            "_value" : "iPad (10th generation)"
          },
          "localComputerRecord" : {
            "_type" : {
              "_name" : "ActionDeviceRecord"
            },
            "busSpeedInMHz" : {
              "_type" : {
                "_name" : "Int"
              },
              "_value" : "100"
            },
            "cpuCount" : {
              "_type" : {
                "_name" : "Int"
              },
              "_value" : "1"
            },
            "cpuKind" : {
              "_type" : {
                "_name" : "String"
              },
              "_value" : "Unknown"
            },
            "cpuSpeedInMHz" : {
              "_type" : {
                "_name" : "Int"
              },
              "_value" : "2400"
            },
            "identifier" : {
              "_type" : {
                "_name" : "String"
              },
              "_value" : "0A8B2720-3E8B-589B-A2E6-92A582C32886"
            },
            "isConcreteDevice" : {
              "_type" : {
                "_name" : "Bool"
              },
              "_value" : "true"
            },
            "logicalCPUCoresPerPackage" : {
              "_type" : {
                "_name" : "Int"
              },
              "_value" : "8"
            },
            "modelCode" : {
              "_type" : {
                "_name" : "String"
              },
              "_value" : "MacBookAir10,1"
            },
            "modelName" : {
              "_type" : {
                "_name" : "String"
              },
              "_value" : "MacBook Air"
            },
            "modelUTI" : {
              "_type" : {
                "_name" : "String"
              },
              "_value" : "com.apple.macbookair-late-2020"
            },
            "name" : {
              "_type" : {
                "_name" : "String"
              },
              "_value" : "My Mac"
            },
            "nativeArchitecture" : {
              "_type" : {
                "_name" : "String"
              },
              "_value" : "x86_64"
            },
            "operatingSystemVersion" : {
              "_type" : {
                "_name" : "String"
              },
              "_value" : "15.0.1"
            },
            "operatingSystemVersionWithBuildNumber" : {
              "_type" : {
                "_name" : "String"
              },
              "_value" : "15.0.1 (24A348)"
            },
            "physicalCPUCoresPerPackage" : {
              "_type" : {
                "_name" : "Int"
              },
              "_value" : "8"
            },
            "platformRecord" : {
              "_type" : {
                "_name" : "ActionPlatformRecord"
              },
              "identifier" : {
                "_type" : {
                  "_name" : "String"
                },
                "_value" : "com.apple.platform.macosx"
              },
              "userDescription" : {
                "_type" : {
                  "_name" : "String"
                },
                "_value" : "macOS"
              }
            },
            "ramSizeInMegabytes" : {
              "_type" : {
                "_name" : "Int"
              },
              "_value" : "8192"
            }
          },
          "targetArchitecture" : {
            "_type" : {
              "_name" : "String"
            },
            "_value" : "arm64"
          },
          "targetDeviceRecord" : {
            "_type" : {
              "_name" : "ActionDeviceRecord"
            },
            "busSpeedInMHz" : {
              "_type" : {
                "_name" : "Int"
              },
              "_value" : "0"
            },
            "cpuCount" : {
              "_type" : {
                "_name" : "Int"
              },
              "_value" : "0"
            },
            "cpuSpeedInMHz" : {
              "_type" : {
                "_name" : "Int"
              },
              "_value" : "0"
            },
            "identifier" : {
              "_type" : {
                "_name" : "String"
              },
              "_value" : "B7C1A209-ACF8-4012-BB21-14B7CDBD3808"
            },
            "isConcreteDevice" : {
              "_type" : {
                "_name" : "Bool"
              },
              "_value" : "true"
            },
            "logicalCPUCoresPerPackage" : {
              "_type" : {
                "_name" : "Int"
              },
              "_value" : "0"
            },
            "modelCode" : {
              "_type" : {
                "_name" : "String"
              },
              "_value" : "iPad13,18"
            },
            "modelName" : {
              "_type" : {
                "_name" : "String"
              },
              "_value" : "iPad (10th generation)"
            },
            "modelUTI" : {
              "_type" : {
                "_name" : "String"
              },
              "_value" : "com.apple.ipad-10-1"
            },
            "name" : {
              "_type" : {
                "_name" : "String"
              },
              "_value" : "iPad (10th generation)"
            },
            "nativeArchitecture" : {
              "_type" : {
                "_name" : "String"
              },
              "_value" : "arm64"
            },
            "operatingSystemVersion" : {
              "_type" : {
                "_name" : "String"
              },
              "_value" : "18.0"
            },
            "operatingSystemVersionWithBuildNumber" : {
              "_type" : {
                "_name" : "String"
              },
              "_value" : "18.0 (22A3351)"
            },
            "physicalCPUCoresPerPackage" : {
              "_type" : {
                "_name" : "Int"
              },
              "_value" : "0"
            },
            "platformRecord" : {
              "_type" : {
                "_name" : "ActionPlatformRecord"
              },
              "identifier" : {
                "_type" : {
                  "_name" : "String"
                },
                "_value" : "com.apple.platform.iphonesimulator"
              },
              "userDescription" : {
                "_type" : {
                  "_name" : "String"
                },
                "_value" : "iOS Simulator"
              }
            },
            "ramSizeInMegabytes" : {
              "_type" : {
                "_name" : "Int"
              },
              "_value" : "0"
            }
          },
          "targetSDKRecord" : {
            "_type" : {
              "_name" : "ActionSDKRecord"
            },
            "identifier" : {
              "_type" : {
                "_name" : "String"
              },
              "_value" : "iphonesimulator18.0"
            },
            "name" : {
              "_type" : {
                "_name" : "String"
              },
              "_value" : "Simulator - iOS 18.0"
            },
            "operatingSystemVersion" : {
              "_type" : {
                "_name" : "String"
              },
              "_value" : "18.0"
            }
          }
        },
        "schemeCommandName" : {
          "_type" : {
            "_name" : "String"
          },
          "_value" : "Test"
        },
        "schemeTaskName" : {
          "_type" : {
            "_name" : "String"
          },
          "_value" : "BuildAndAction"
        },
        "startedTime" : {
          "_type" : {
            "_name" : "Date"
          },
          "_value" : "2024-11-02T22:11:40.913+0900"
        },
        "testPlanName" : {
          "_type" : {
            "_name" : "String"
          },
          "_value" : "swiftUI_XCUITestTests"
        },
        "title" : {
          "_type" : {
            "_name" : "String"
          },
          "_value" : "Testing project swiftUI_XCUITest with scheme swiftUI_XCUITestTests"
        }
      }
    ]
  },
  "issues" : {
    "_type" : {
      "_name" : "ResultIssueSummaries"
    }
  },
  "metadataRef" : {
    "_type" : {
      "_name" : "Reference"
    },
    "id" : {
      "_type" : {
        "_name" : "String"
      },
      "_value" : "0~RLWO4o7l92m0WlrzOfLUvW2XJ-BP-m0veVhLB8SdnCC6Qg-W5AYnKBA9oJVHvWk9kr2A1lSVJHLIzb7nD5vluA=="
    },
    "targetType" : {
      "_type" : {
        "_name" : "TypeDefinition"
      },
      "name" : {
        "_type" : {
          "_name" : "String"
        },
        "_value" : "ActionsInvocationMetadata"
      }
    }
  },
  "metrics" : {
    "_type" : {
      "_name" : "ResultMetrics"
    },
    "totalCoveragePercentage" : {
      "_type" : {
        "_name" : "Double"
      },
      "_value" : "0.7070707070707071"
    }
  }
}
